wyb/__init__.py
wyb/wyb.py
wyb-0.0.1.dist-info/DESCRIPTION.rst
wyb-0.0.1.dist-info/METADATA
wyb-0.0.1.dist-info/RECORD
wyb-0.0.1.dist-info/WHEEL
wyb-0.0.1.dist-info/metadata.json
wyb-0.0.1.dist-info/top_level.txt
